sail/__init__.py
sail/common/decorators.py
sail/common/helper.py
sail/common/mixin.py
sail/common/progress_bar.py
sail/common/scorer.py
sail/drift_detection/drift_detector.py
sail/model_selector/__init__.py
sail/model_selector/base.py
sail/model_selector/holdout_best_model.py
sail/model_selector/prequential_best_model.py
sail/models/__init__.py
sail/models/base.py
sail/models/auto_ml/__init__.py
sail/models/auto_ml/auto_pipeline.py
sail/models/auto_ml/base_strategy.py
sail/models/auto_ml/pipeline_strategy.py
sail/models/auto_ml/searcher.py
sail/models/auto_ml/tune.py
sail/models/ensemble/__init__.py
sail/models/ensemble/base.py
sail/models/ensemble/distAggregateClassifier.py
sail/models/ensemble/distAggregateRegressor.py
sail/models/ensemble/distEWARegressor.py
sail/models/keras/__init__.py
sail/models/keras/base.py
sail/models/keras/oselm.py
sail/models/keras/sequential.py
sail/models/keras/wglstm.py
sail/models/native/__init__.py
sail/models/native/base.py
sail/models/native/ielm.py
sail/models/native/isvm.py
sail/models/native/lasvm.py
sail/models/native/learn_pp.py
sail/models/native/robust_iml.py
sail/models/river/__init__.py
sail/models/river/anomaly.py
sail/models/river/base.py
sail/models/river/ensemble.py
sail/models/river/forest.py
sail/models/river/linear_model.py
sail/models/river/naive_bayes.py
sail/models/river/neighbors.py
sail/models/sklearn/__init__.py
sail/models/sklearn/base.py
sail/models/sklearn/cluster.py
sail/models/sklearn/linear_model.py
sail/models/sklearn/naive_bayes.py
sail/models/torch/__init__.py
sail/models/torch/base.py
sail/models/torch/conv_net.py
sail/models/torch/dataset.py
sail/models/torch/fcn.py
sail/models/torch/inceptiontime.py
sail/models/torch/layers.py
sail/models/torch/light_lstm.py
sail/models/torch/lstm.py
sail/models/torch/lstm_fcn.py
sail/models/torch/nn.py
sail/models/torch/onn_hbp.py
sail/models/torch/os_cnn.py
sail/models/torch/rnn.py
sail/models/torch/rocket.py
sail/models/torch/tcn.py
sail/pipeline/__init__.py
sail-0.12.1.dist-info/LICENSE
sail-0.12.1.dist-info/METADATA
sail-0.12.1.dist-info/WHEEL
sail-0.12.1.dist-info/top_level.txt
sail-0.12.1.dist-info/RECORD
