Metadata-Version: 2.1
Name: sail
Version: 0.12.1
Summary: Python package for streaming data and incremental learning
Author-email: Dhaval Salwala <dhaval.vinodbhai.salwala@ibm.com>, Seshu Tirupathi <seshutir@ie.ibm.com>
License: MIT
Project-URL: repository, https://github.com/IBM/sail
Classifier: Development Status :: 4 - Beta
Classifier: Intended Audience :: Developers
Classifier: Intended Audience :: Science/Research
Classifier: Topic :: Software Development :: Libraries :: Python Modules
Classifier: License :: OSI Approved :: MIT License
Classifier: Programming Language :: Python
Classifier: Programming Language :: Python :: 3
Classifier: Programming Language :: Python :: 3.8
Classifier: Programming Language :: Python :: 3.9
Classifier: Programming Language :: Python :: 3.10
Requires-Python: >=3.10
License-File: LICENSE
Requires-Dist: logzero
Requires-Dist: dill
Requires-Dist: tqdm
Requires-Dist: seaborn ==0.12.2
Requires-Dist: numpy >=1.23
Requires-Dist: scipy >=1.10
Requires-Dist: pandas >=2.0
Requires-Dist: opentelemetry-api
Requires-Dist: opentelemetry-sdk
Requires-Dist: opentelemetry-exporter-otlp
Requires-Dist: tensorboard >=2.11
Requires-Dist: matplotlib ==3.7.2
Requires-Dist: scikit-learn >=1.2
Provides-Extra: all
Requires-Dist: sail[tensorflow] ; extra == 'all'
Requires-Dist: sail[pytorch] ; extra == 'all'
Requires-Dist: sail[river] ; extra == 'all'
Requires-Dist: sail[ray] ; extra == 'all'
Requires-Dist: sail[dev] ; extra == 'all'
Requires-Dist: sail[examples] ; extra == 'all'
Requires-Dist: sail[tests] ; extra == 'all'
Provides-Extra: dev
Requires-Dist: black ; extra == 'dev'
Requires-Dist: pylint ; extra == 'dev'
Provides-Extra: examples
Requires-Dist: ipykernel ; extra == 'examples'
Requires-Dist: plotly ; extra == 'examples'
Requires-Dist: nbformat ; extra == 'examples'
Requires-Dist: gdown ; extra == 'examples'
Requires-Dist: liac-arff ; extra == 'examples'
Provides-Extra: pytorch
Requires-Dist: torch >=2.0 ; extra == 'pytorch'
Requires-Dist: skorch ; extra == 'pytorch'
Provides-Extra: ray
Requires-Dist: ray <=2.6.3,>=2.5 ; extra == 'ray'
Requires-Dist: hyperopt ; extra == 'ray'
Requires-Dist: tune-sklearn ; extra == 'ray'
Provides-Extra: river
Requires-Dist: river ==0.18.* ; extra == 'river'
Provides-Extra: tensorflow
Requires-Dist: tensorflow <=2.13,>=2.7 ; extra == 'tensorflow'
Requires-Dist: scikeras ; extra == 'tensorflow'
Requires-Dist: tensorflow-addons ; extra == 'tensorflow'
Provides-Extra: tensorflow_arm64
Requires-Dist: tensorflow-macos <=2.13,>=2.7 ; extra == 'tensorflow_arm64'
Requires-Dist: scikeras ; extra == 'tensorflow_arm64'
Requires-Dist: tensorflow-addons ; extra == 'tensorflow_arm64'
Provides-Extra: tensorflow_cpu
Requires-Dist: tensorflow-cpu <=2.13,>=2.7 ; extra == 'tensorflow_cpu'
Requires-Dist: scikeras ; extra == 'tensorflow_cpu'
Requires-Dist: tensorflow-addons ; extra == 'tensorflow_cpu'
Provides-Extra: tests
Requires-Dist: pytest ; extra == 'tests'
Requires-Dist: nbmake ; extra == 'tests'
Requires-Dist: pytest-xdist ; extra == 'tests'
Requires-Dist: pytest-console-scripts ; extra == 'tests'
